CHANGELOG
LICENSE.txt
MANIFEST.in
setup.cfg
setup.py
PyBlox.egg-info/PKG-INFO
PyBlox.egg-info/SOURCES.txt
PyBlox.egg-info/dependency_links.txt
PyBlox.egg-info/entry_points.txt
PyBlox.egg-info/not-zip-safe
PyBlox.egg-info/requires.txt
PyBlox.egg-info/top_level.txt
pyblox/__init__.py
pyblox/app_router.py
pyblox/application.py
pyblox/commands.py
pyblox/configuration.py
pyblox/decorators.py
pyblox/logger.py
pyblox/middleware.py
pyblox/tmplt.py
pyblox/util.py
pyblox/templates/MANIFEST.in_tmpl
pyblox/templates/__init__.py
pyblox/templates/development.ini_tmpl
pyblox/templates/setup.cfg_tmpl
pyblox/templates/setup.py_tmpl
pyblox/templates/+package+/__init__.py
pyblox/templates/+package+/websetup.py_tmpl
pyblox/templates/+package+/application/__init__.py_tmpl
pyblox/templates/+package+/application/config_factory.py_tmpl
pyblox/templates/+package+/application/route_factory.py_tmpl
pyblox/templates/+package+/controllers/__init__.py_tmpl
pyblox/templates/+package+/controllers/auth.py_tmpl
pyblox/templates/+package+/controllers/base.py_tmpl
pyblox/templates/+package+/controllers/core.py_tmpl
pyblox/templates/+package+/controllers/root.py_tmpl
pyblox/templates/+package+/lib/__init__.py_tmpl
pyblox/templates/+package+/lib/app_globals.py_tmpl
pyblox/templates/+package+/lib/base.py_tmpl
pyblox/templates/+package+/lib/errors.py_tmpl
pyblox/templates/+package+/lib/forms.py_tmpl
pyblox/templates/+package+/lib/helpers.py
pyblox/templates/+package+/lib/utils.py_tmpl
pyblox/templates/+package+/model/__init__.py_tmpl
pyblox/templates/+package+/model/base.py_tmpl
pyblox/templates/+package+/model/core.py_tmpl
pyblox/templates/+package+/model/mapping.py_tmpl
pyblox/templates/+package+/model/util.py_tmpl
pyblox/templates/+package+/static/img/10.jpg
pyblox/templates/+package+/static/img/11.jpg
pyblox/templates/+package+/static/img/12.jpg
pyblox/templates/+package+/static/img/8.jpg
pyblox/templates/+package+/static/img/9.jpg
pyblox/templates/+package+/static/img/arrow.png
pyblox/templates/+package+/static/img/avatar.png
pyblox/templates/+package+/static/img/loading.gif
pyblox/templates/+package+/static/img/offline.png
pyblox/templates/+package+/static/img/online.png
