Metadata-Version: 1.1
Name: PyBlox
Version: 0.1-r0
Summary: A Python MVC web framework.
Home-page: http://www.pyblox.org
Author: Noel Morgan
Author-email: noel@pyblox.org
License: MIT
Keywords: python sqlalchemy angularjs framework responsive bootstrap admin
Platform: UNKNOWN
Classifier: Environment :: Web Environment
